mult_flow/__init__.py
mult_flow/mult.py
mult_flow-1.0.2.dist-info/METADATA
mult_flow-1.0.2.dist-info/WHEEL
mult_flow-1.0.2.dist-info/RECORD
